folium_arrow_icon.py
folium_arrow_icon-0.1.3.dist-info/METADATA
folium_arrow_icon-0.1.3.dist-info/WHEEL
folium_arrow_icon-0.1.3.dist-info/licenses/LICENSE
folium_arrow_icon-0.1.3.dist-info/RECORD
