Metadata-Version: 2.3
Name: folium-arrow-icon
Version: 0.1.3
Summary: Simple arrow (vector/quiver) icon for folium
Project-URL: Documentation, https://folium-arrow-icon.readthedocs.io
Project-URL: Issues, https://github.com/paqira/folium-arrow-icon/issues
Project-URL: Source, https://github.com/paqira/folium-arrow-icon
Author-email: Kentaro Tatsumi <paqira.2019@gmail.com>
License: MIT
License-File: LICENSE
Keywords: arrow,folium,icon,quiver,vector field
Classifier: License :: OSI Approved :: MIT License
Classifier: Operating System :: OS Independent
Classifier: Programming Language :: Python
Classifier: Programming Language :: Python :: 3.8
Classifier: Programming Language :: Python :: 3.9
Classifier: Programming Language :: Python :: 3.10
Classifier: Programming Language :: Python :: 3.11
Classifier: Programming Language :: Python :: 3.12
Classifier: Programming Language :: Python :: 3.13
Classifier: Topic :: Scientific/Engineering :: GIS
Classifier: Topic :: Scientific/Engineering :: Visualization
Requires-Python: >=3.8
